yaml_configuration/__init__.py
yaml_configuration/config.py
yaml_configuration-0.3.2.data/data/VERSION
yaml_configuration-0.3.2.dist-info/licenses/AUTHORS
yaml_configuration-0.3.2.dist-info/licenses/LICENSE
yaml_configuration-0.3.2.dist-info/METADATA
yaml_configuration-0.3.2.dist-info/WHEEL
yaml_configuration-0.3.2.dist-info/top_level.txt
yaml_configuration-0.3.2.dist-info/zip-safe
yaml_configuration-0.3.2.dist-info/RECORD
