Metadata-Version: 2.4
Name: yaml_configuration
Version: 0.3.2
Summary: A python module to easily read from and write to yaml config files.
Home-page: https://github.com/DLR-RM/python-yaml-configuration
Author: Sebastian Brunner
Author-email: sebastian.brunner@dlr.de
Maintainer: Sebastian Brunner
Maintainer-email: sebastian.brunner@dlr.de
License: BSD
Keywords: yaml,configuration
Classifier: Development Status :: 5 - Production/Stable
Classifier: Intended Audience :: Developers
Classifier: Intended Audience :: Information Technology
Classifier: Intended Audience :: Science/Research
Classifier: License :: OSI Approved :: BSD License
Classifier: Operating System :: OS Independent
Classifier: Programming Language :: Python :: 2
Classifier: Programming Language :: Python :: 3
Classifier: Topic :: Software Development :: Libraries :: Python Modules
Classifier: Topic :: Utilities
Requires-Python: >=2.6
License-File: LICENSE
License-File: AUTHORS
Requires-Dist: pyyaml>=5.1
Dynamic: author
Dynamic: author-email
Dynamic: classifier
Dynamic: description
Dynamic: home-page
Dynamic: keywords
Dynamic: license
Dynamic: license-file
Dynamic: maintainer
Dynamic: maintainer-email
Dynamic: requires-dist
Dynamic: requires-python
Dynamic: summary
